odoo10_addon_stock_operating_unit-10.0.1.1.0-nspkg.pth
odoo/addons/stock_operating_unit/README.rst
odoo/addons/stock_operating_unit/__init__.py
odoo/addons/stock_operating_unit/__manifest__.py
odoo/addons/stock_operating_unit/hooks.py
odoo/addons/stock_operating_unit/data/stock_data.xml
odoo/addons/stock_operating_unit/demo/stock_demo.xml
odoo/addons/stock_operating_unit/model/__init__.py
odoo/addons/stock_operating_unit/model/stock.py
odoo/addons/stock_operating_unit/security/stock_security.xml
odoo/addons/stock_operating_unit/static/description/icon.png
odoo/addons/stock_operating_unit/tests/__init__.py
odoo/addons/stock_operating_unit/tests/test_stock_operating_unit.py
odoo/addons/stock_operating_unit/tests/test_stock_picking.py
odoo/addons/stock_operating_unit/tests/test_stock_security.py
odoo/addons/stock_operating_unit/view/stock.xml
odoo10_addon_stock_operating_unit-10.0.1.1.0.dist-info/METADATA
odoo10_addon_stock_operating_unit-10.0.1.1.0.dist-info/WHEEL
odoo10_addon_stock_operating_unit-10.0.1.1.0.dist-info/namespace_packages.txt
odoo10_addon_stock_operating_unit-10.0.1.1.0.dist-info/top_level.txt
odoo10_addon_stock_operating_unit-10.0.1.1.0.dist-info/RECORD
